dj_swift_auth/__init__.py
dj_swift_auth/admin.py
dj_swift_auth/apps.py
dj_swift_auth/manager.py
dj_swift_auth/models.py
dj_swift_auth/response.py
dj_swift_auth/serializers.py
dj_swift_auth/services.py
dj_swift_auth/tests.py
dj_swift_auth/urls.py
dj_swift_auth/utils.py
dj_swift_auth/views.py
django_swift_auth-1.0.dist-info/LICENSE
django_swift_auth-1.0.dist-info/METADATA
django_swift_auth-1.0.dist-info/WHEEL
django_swift_auth-1.0.dist-info/top_level.txt
django_swift_auth-1.0.dist-info/RECORD
