Metadata-Version: 2.1
Name: django-swift-auth
Version: 1.0
Summary: A Django app to rest framework custom user registration and authentication.
Home-page: https://github.com/mbrsagor/dj-rest-register
Author: Bozlur Rosid Sagor
Author-email: brshagor.cse@gmail.com
Maintainer-email: mbrsagor@gmail.com
License: MIT
Keywords: drf-authentication drf-auth-login drf-custom-registration
Platform: UNKNOWN
Classifier: Environment :: Web Environment
Classifier: Framework :: Django
Classifier: Intended Audience :: Developers
Classifier: License :: OSI Approved :: MIT License
Classifier: Operating System :: OS Independent
Classifier: Programming Language :: Python
Classifier: Programming Language :: Python :: 3
Classifier: Programming Language :: Python :: 3 :: Only
Classifier: Programming Language :: Python :: 3.6
Classifier: Programming Language :: Python :: 3.7
Classifier: Programming Language :: Python :: 3.8
Classifier: Topic :: Software Development :: Libraries :: Python Modules
License-File: LICENSE
